coolquote/__init__.py
coolquote/model_loader.py
coolquote/quote_generator.py
coolquote-0.1.0.dist-info/METADATA
coolquote-0.1.0.dist-info/WHEEL
coolquote-0.1.0.dist-info/top_level.txt
coolquote-0.1.0.dist-info/RECORD
